better_diff/__init__.py
better_diff/unified_plus.py
better_diff-0.1.4.dist-info/LICENSE
better_diff-0.1.4.dist-info/METADATA
better_diff-0.1.4.dist-info/WHEEL
better_diff-0.1.4.dist-info/RECORD
