Metadata-Version: 2.1
Name: better_diff
Version: 0.1.4
Summary: A simple library for printing better diffs based on the stdlib unified_diff format.
Home-page: https://ni.github.io/py_better_diff/
License: MIT
Keywords: diff,diff_format,diff_printer
Author: Matthew Shafer
Author-email: 23644905+mshafer-NI@users.noreply.github.com
Requires-Python: >=3.8,<4.0
Classifier: License :: OSI Approved :: MIT License
Classifier: Programming Language :: Python :: 3
Classifier: Programming Language :: Python :: 3.8
Classifier: Programming Language :: Python :: 3.9
Classifier: Programming Language :: Python :: 3.10
Classifier: Programming Language :: Python :: 3.11
Classifier: Programming Language :: Python :: 3.12
Project-URL: Repository, https://github.com/ni/py_better_diff/
